ks_zha-0.0.2.dist-info/licenses/LICENSE
zha/__init__.py
zha/async_.py
zha/const.py
zha/debounce.py
zha/decorators.py
zha/event.py
zha/exceptions.py
zha/mixins.py
zha/units.py
zha/application/__init__.py
zha/application/const.py
zha/application/discovery.py
zha/application/gateway.py
zha/application/helpers.py
zha/application/registries.py
zha/application/platforms/__init__.py
zha/application/platforms/device_tracker.py
zha/application/platforms/helpers.py
zha/application/platforms/select.py
zha/application/platforms/siren.py
zha/application/platforms/switch.py
zha/application/platforms/update.py
zha/application/platforms/alarm_control_panel/__init__.py
zha/application/platforms/alarm_control_panel/const.py
zha/application/platforms/binary_sensor/__init__.py
zha/application/platforms/binary_sensor/const.py
zha/application/platforms/button/__init__.py
zha/application/platforms/button/const.py
zha/application/platforms/climate/__init__.py
zha/application/platforms/climate/const.py
zha/application/platforms/cover/__init__.py
zha/application/platforms/cover/const.py
zha/application/platforms/fan/__init__.py
zha/application/platforms/fan/const.py
zha/application/platforms/fan/helpers.py
zha/application/platforms/light/__init__.py
zha/application/platforms/light/const.py
zha/application/platforms/light/helpers.py
zha/application/platforms/lock/__init__.py
zha/application/platforms/lock/const.py
zha/application/platforms/number/__init__.py
zha/application/platforms/number/const.py
zha/application/platforms/sensor/__init__.py
zha/application/platforms/sensor/const.py
zha/zigbee/__init__.py
zha/zigbee/device.py
zha/zigbee/endpoint.py
zha/zigbee/group.py
zha/zigbee/cluster_handlers/__init__.py
zha/zigbee/cluster_handlers/closures.py
zha/zigbee/cluster_handlers/const.py
zha/zigbee/cluster_handlers/general.py
zha/zigbee/cluster_handlers/helpers.py
zha/zigbee/cluster_handlers/homeautomation.py
zha/zigbee/cluster_handlers/hvac.py
zha/zigbee/cluster_handlers/lighting.py
zha/zigbee/cluster_handlers/lightlink.py
ks_zha-0.0.2.dist-info/METADATA
ks_zha-0.0.2.dist-info/WHEEL
ks_zha-0.0.2.dist-info/top_level.txt
ks_zha-0.0.2.dist-info/RECORD
