Metadata-Version: 2.4
Name: ks-zha
Version: 0.0.2
Summary: Library implementing ZHA for Home Assistant
Author-email: "David F. Mulcahey" <david.mulcahey@icloud.com>
License: Apache-2.0
Project-URL: repository, https://github.com/zigpy/zha
Requires-Python: >=3.12
License-File: LICENSE
Requires-Dist: zigpy==0.77.1
Requires-Dist: bellows==0.43.0
Requires-Dist: zigpy-znp==0.13.1
Requires-Dist: zigpy-deconz==0.24.1
Requires-Dist: zigpy-xbee==0.21.0
Requires-Dist: zigpy-zigate==0.13.2
Requires-Dist: zha-quirks==0.0.134
Requires-Dist: pyserial==3.5
Requires-Dist: pyserial-asyncio-fast
Provides-Extra: testing
Requires-Dist: pytest; extra == "testing"
Dynamic: license-file
